Workbook

Sheet Quote Calculator
A1: Client Fee Quote
A2: Fill in the yellow cells. Everything else calculates from the Rate Card tab. Example values shown – overwrite for each client.
A4: CLIENT PROFILE
A5: Client name | B5: Example Ltd
A6: Entity type | B6: Limited Company
A7: Turnover band | B7: £90k–£250k
A8: Complexity | B8: Standard
A9: Record quality | B9: Average
A10: Bookkeeping transactions per month | B10: 120
A11: Bank/card accounts | B11: 2
A12: Invoices processed per month | B12: 30
A13: Multi-currency? (Y/N) | B13: N
A14: VAT scheme (None/Standard/Flat Rate) | B14: Standard
A15: Partial exemption? (Y/N) | B15: N
A16: Employees on payroll | B16: 3
A17: Pay frequency (Monthly/Weekly) | B17: Monthly
A18: Auto-enrolment pension? (Y/N) | B18: Y
A19: P11Ds per year | B19: 1
A20: CIS contractor? (Y/N) | B20: N
A21: Subcontractors per month | B21: 0
A22: Directors/individuals needing SA returns | B22: 2
A23: Rental properties (total across returns) | B23: 1
A24: CGT disposals | B24: 0
A25: Returns with foreign income | B25: 0
A26: MTD ITSA quarterly updates per year | B26: 0
A27: Dividends declared per year | B27: 4
A28: Management accounts packs per year | B28: 4
A29: Registered office service? (Y/N) | B29: Y
A30: Pay annually upfront? (Y/N) | B30: N
A32: Multiplier (complexity × records) | B32: =INDEX('Rate Card'!$B$52:$B$54,MATCH($B$8,'Rate Card'!$A$52:$A$54,0))*INDEX('Rate Card'!$E$52:$E$54,MATCH($B$9,'Rate Card'!$D$52:$D$54,0)) -> 1.15
A33: Is a company? (CT600, sec, dividends) | B33: =IF(OR($B$6="Limited Company",$B$6="LLP"),"Y","N") -> Y
A35: Service | B35: Include? (Y/N) | C35: Annual fee (£) | D35: Monthly equivalent (£) | E35: Basis
A36: Bookkeeping | B36: Y | C36: =IF(B36="Y",('Rate Card'!$B$5+MAX(0,$B$10-'Rate Card'!$B$6)*'Rate Card'!$B$7+MAX(0,$B$11-1)*'Rate Card'!$B$8+$B$12*'Rate Card'!$B$10+IF($B$13="Y",'Rate Card'!$B$9,0))*12*$B$32,0) -> 1945.8 | D36: =C36/12 -> 162.15 | E36: Base + extra transactions, accounts & invoices × multiplier
A37: VAT returns | B37: =IF($B$14="None","N","Y") -> Y | C37: =IF(B37="Y",4*IF($B$14="Flat Rate",'Rate Card'!$B$13,'Rate Card'!$B$12)+IF($B$15="Y",'Rate Card'!$B$14,0),0) -> 300 | D37: =C37/12 -> 25 | E37: 4 quarterly returns
A38: Payroll | B38: =IF($B$16>0,"Y","N") -> Y | C38: =IF(B38="Y",IF($B$17="Weekly",52,12)*MAX('Rate Card'!$B$18,$B$16*'Rate Card'!$B$17)+IF($B$18="Y",12*'Rate Card'!$B$19,0)+$B$19*'Rate Card'!$B$20,0) -> 435 | D38: =C38/12 -> 36.25 | E38: Per run (min charge) + pension + P11Ds
A39: CIS returns | B39: =$B$20 -> N | C39: =IF(B39="Y",12*('Rate Card'!$B$21+$B$21*'Rate Card'!$B$22),0) -> 0 | D39: =C39/12 -> 0 | E39: Monthly CIS300
A40: Year-end accounts | B40: Y | C40: =IF(B40="Y",INDEX('Rate Card'!$B$58:$F$62,MATCH($B$6,'Rate Card'!$A$58:$A$62,0),MATCH($B$7,'Rate Card'!$B$57:$F$57,0))*$B$32,0) -> 977.5 | D40: =C40/12 -> 81.458333 | E40: Entity × turnover table × multiplier
A41: Corporation tax return (CT600) | B41: =IF($B$6="Limited Company","Y","N") -> Y | C41: =IF(B41="Y",'Rate Card'!$B$24,0) -> 250 | D41: =C41/12 -> 20.833333 | E41: Annual
A42: Partnership return (SA800) | B42: =IF(OR($B$6="Partnership",$B$6="LLP"),"Y","N") -> N | C42: =IF(B42="Y",'Rate Card'!$B$29,0) -> 0 | D42: =C42/12 -> 0 | E42: Annual
A43: Self assessment returns | B43: =IF($B$22>0,"Y","N") -> Y | C43: =IF(B43="Y",$B$22*'Rate Card'!$B$25+$B$23*'Rate Card'!$B$26+$B$24*'Rate Card'!$B$27+$B$25*'Rate Card'!$B$28,0) -> 475 | D43: =C43/12 -> 39.583333 | E43: Per return + add-ons
A44: MTD for Income Tax quarterly updates | B44: =IF($B$26>0,"Y","N") -> N | C44: =IF(B44="Y",$B$26*'Rate Card'!$B$30,0) -> 0 | D44: =C44/12 -> 0 | E44: Per update
A45: Confirmation statement | B45: =$B$33 -> Y | C45: =IF(B45="Y",'Rate Card'!$B$32+'Rate Card'!$B$33,0) -> 110 | D45: =C45/12 -> 9.1666667 | E45: Fee + Companies House disbursement
A46: Registered office | B46: =$B$29 -> Y | C46: =IF(B46="Y",'Rate Card'!$B$34,0) -> 120 | D46: =C46/12 -> 10 | E46: Annual
A47: Dividend paperwork | B47: =IF(AND($B$33="Y",$B$27>0),"Y","N") -> Y | C47: =IF(B47="Y",$B$27*'Rate Card'!$B$35,0) -> 100 | D47: =C47/12 -> 8.3333333 | E47: Per dividend
A48: Management accounts | B48: =IF($B$28>0,"Y","N") -> Y | C48: =IF(B48="Y",$B$28*'Rate Card'!$B$37,0) -> 600 | D48: =C48/12 -> 50 | E48: Per pack
A49: Recurring fees subtotal | C49: =SUM(C36:C48) -> 5313.3 | D49: =C49/12 -> 442.775
A50: Minimum fee top-up | C50: =MAX(0,'Rate Card'!$B$47*12-C49) -> 0 | D50: =C50/12 -> 0
A51: Less: annual upfront discount | C51: =-IF($B$30="Y",(C49+C50)*'Rate Card'!$B$48,0) -> 0 | D51: =C51/12 -> 0
A52: Recurring fee (ex VAT) | C52: =C49+C50+C51 -> 5313.3 | D52: =C52/12 -> 442.775
A53: VAT | C53: =C52*'Rate Card'!$B$49 -> 1062.66 | D53: =C53/12 -> 88.555
A54: RECURRING FEE INC VAT | C54: =C52+C53 -> 6375.96 | D54: =C54/12 -> 531.33
A56: One-off / project work | B56: Quantity | C56: Fee (£) | D56: Unit price (£)
A57: Company formation | B57: 0 | C57: =B57*D57 -> 0 | D57: ='Rate Card'!$B$40 -> 150
A58: VAT registration | B58: 0 | C58: =B58*D58 -> 0 | D58: ='Rate Card'!$B$15 -> 100
A59: Alphabet share restructure | B59: 0 | C59: =B59*D59 -> 0 | D59: ='Rate Card'!$B$41 -> 450
A60: Share transfer / allotment | B60: 0 | C60: =B60*D60 -> 0 | D60: ='Rate Card'!$B$42 -> 150
A61: Dormant company accounts | B61: 0 | C61: =B61*D61 -> 0 | D61: ='Rate Card'!$B$43 -> 150
A62: Cash flow forecast / budget | B62: 0 | C62: =B62*D62 -> 0 | D62: ='Rate Card'!$B$38 -> 350
A63: R&D tax claim | B63: 0 | C63: =B63*D63 -> 0 | D63: ='Rate Card'!$B$44 -> 1500
A64: Advisory hours | B64: 0 | C64: =B64*D64 -> 0 | D64: ='Rate Card'!$B$45 -> 90
A65: Company secretarial items (Co Sec Menu tab) | B65: see tab | C65: ='Co Sec Menu'!$G$3 -> 0
A66: One-off fees (ex VAT) | C66: =SUM(C57:C65) -> 0
A67: One-off fees inc VAT | C67: =C66*(1+'Rate Card'!$B$49) -> 0
A69: Note: alphabet shares carry settlements-legislation and dividend-waiver risk – the restructure fee includes a short tax note; don't do the paperwork without it.

Sheet Rate Card
A1: UniFinancial Solutions – Rate Card (edit blue figures to set your prices)
A2: All prices exclude VAT. Blue = your input. Figures are starting suggestions based on typical UK small-practice fees – review against your own market.
A4: Bookkeeping
A5: Base fee (includes transactions below) | B5: 60 | C5: per month
A6: Transactions included in base | B6: 50 | C6: per month
A7: Each additional transaction | B7: 0.8 | C7: per transaction
A8: Each bank/card account beyond the first | B8: 10 | C8: per month
A9: Multi-currency handling | B9: 20 | C9: per month
A10: Sales/purchase invoice processing | B10: 0.5 | C10: per invoice
A11: VAT
A12: VAT return – standard/cash accounting | B12: 75 | C12: per return
A13: VAT return – flat rate scheme | B13: 50 | C13: per return
A14: Partial exemption calculations | B14: 150 | C14: per year
A15: VAT registration (one-off) | B15: 100 | C15: one-off
A16: Payroll
A17: Per employee per pay run | B17: 5 | C17: per employee/run
A18: Minimum charge per pay run | B18: 20 | C18: per run
A19: Pension auto-enrolment administration | B19: 10 | C19: per month
A20: P11D per employee (incl. P11D(b)) | B20: 75 | C20: per P11D
A21: CIS monthly return | B21: 25 | C21: per month
A22: Per subcontractor verified/paid | B22: 2 | C22: per sub/month
A23: Tax returns
A24: Corporation tax return (CT600) | B24: 250 | C24: per year
A25: Self assessment return – simple | B25: 200 | C25: per return
A26: Add per rental property | B26: 75 | C26: per property
A27: Add per capital gains disposal | B27: 150 | C27: per disposal
A28: Add foreign income | B28: 100 | C28: per return
A29: Partnership tax return (SA800) | B29: 250 | C29: per year
A30: MTD for Income Tax quarterly update | B30: 40 | C30: per update
A31: Company secretarial
A32: Confirmation statement (our fee) | B32: 60 | C32: per year
A33: Companies House filing fee (disbursement – check current fee) | B33: 50 | C33: per year
A34: Registered office address | B34: 120 | C34: per year
A35: Dividend vouchers & board minutes | B35: 25 | C35: per dividend
A36: Management information
A37: Management accounts pack | B37: 150 | C37: per pack
A38: Cash flow forecast / budget | B38: 350 | C38: per forecast
A39: One-off / project work
A40: Company formation | B40: 150 | C40: one-off
A41: Alphabet share restructure (articles, resolutions, filings, tax note) | B41: 450 | C41: one-off
A42: Share transfer / allotment | B42: 150 | C42: one-off
A43: Dormant company accounts | B43: 150 | C43: per year
A44: R&D tax claim (minimum) | B44: 1500 | C44: per claim
A45: Advisory / ad hoc work | B45: 90 | C45: per hour
A46: Adjustments
A47: Minimum monthly fee (all recurring services) | B47: 50 | C47: per month
A48: Discount for annual fee paid upfront | B48: 0.05 | C48: of recurring fee
A49: VAT charged on your fees (0% if not registered) | B49: 0.2 | C49: rate
A51: Complexity multiplier | D51: Record quality multiplier
A52: Simple | B52: 0.9 | D52: Good | E52: 1
A53: Standard | B53: 1 | D53: Average | E53: 1.15
A54: Complex | B54: 1.3 | D54: Poor | E54: 1.35
A56: Year-end accounts fee by entity and turnover
A57: Entity | B57: Under £90k | C57: £90k–£250k | D57: £250k–£500k | E57: £500k–£1m | F57: Over £1m
A58: Sole Trader | B58: 300 | C58: 450 | D58: 650 | E58: 900 | F58: 1200
A59: Partnership | B59: 400 | C59: 550 | D59: 800 | E59: 1100 | F59: 1500
A60: Limited Company | B60: 650 | C60: 850 | D60: 1150 | E60: 1500 | F60: 2000
A61: LLP | B61: 750 | C61: 950 | D61: 1250 | E61: 1600 | F61: 2100
A62: Landlord (property only) | B62: 250 | C62: 350 | D62: 500 | E62: 700 | F62: 900

Sheet Co Sec Menu
A1: Company secretarial menu – FCLS supplier costs (Price List Feb 2026) with your resale price
A2: Your markup on FCLS cost | B2: 0.5 | C2: Round resale price up to nearest £ | E2: 5
A3: Enter quantities in column H for a client quote; the total feeds the Quote Calculator one-off section → | F3: Quote total (ex VAT) | G3: =SUM(G6:G106) -> 0
A5: Category | B5: Service | C5: FCLS price | D5: FCLS VAT basis | E5: FCLS cost ex VAT | F5: Your resale price (ex VAT) | G5: Line total | H5: Qty | I5: Your current Rate Card price | J5: Note
A6: Company formation
A7: Company formation | B7: Private Limited | C7: 153 | D7: inc VAT | E7: =IF(ISNUMBER(C7),IF(D7="inc VAT",C7/1.2,C7),0) -> 127.5 | F7: =IF(E7=0,"POA",CEILING(E7*(1+$B$2),$E$2)) -> 195 | G7: =IF(ISNUMBER(F7),F7*H7,0) -> 0 | H7: 0 | I7: ='Rate Card'!$B$40 -> 150 | J7: Includes Companies House fee (no VAT on that part) – ex-VAT cost is approximate
A8: Company formation | B8: Flat Management | C8: 223 | D8: inc VAT | E8: =IF(ISNUMBER(C8),IF(D8="inc VAT",C8/1.2,C8),0) -> 185.83333 | F8: =IF(E8=0,"POA",CEILING(E8*(1+$B$2),$E$2)) -> 280 | G8: =IF(ISNUMBER(F8),F8*H8,0) -> 0 | H8: 0
A9: Company formation | B9: Charity | C9: 258 | D9: inc VAT | E9: =IF(ISNUMBER(C9),IF(D9="inc VAT",C9/1.2,C9),0) -> 215 | F9: =IF(E9=0,"POA",CEILING(E9*(1+$B$2),$E$2)) -> 325 | G9: =IF(ISNUMBER(F9),F9*H9,0) -> 0 | H9: 0
A10: Company formation | B10: Guarantee | C10: 223 | D10: inc VAT | E10: =IF(ISNUMBER(C10),IF(D10="inc VAT",C10/1.2,C10),0) -> 185.83333 | F10: =IF(E10=0,"POA",CEILING(E10*(1+$B$2),$E$2)) -> 280 | G10: =IF(ISNUMBER(F10),F10*H10,0) -> 0 | H10: 0
A11: Company formation | B11: PLC | C11: 218 | D11: inc VAT | E11: =IF(ISNUMBER(C11),IF(D11="inc VAT",C11/1.2,C11),0) -> 181.66667 | F11: =IF(E11=0,"POA",CEILING(E11*(1+$B$2),$E$2)) -> 275 | G11: =IF(ISNUMBER(F11),F11*H11,0) -> 0 | H11: 0
A12: Company formation | B12: CIC | C12: 273 | D12: inc VAT | E12: =IF(ISNUMBER(C12),IF(D12="inc VAT",C12/1.2,C12),0) -> 227.5 | F12: =IF(E12=0,"POA",CEILING(E12*(1+$B$2),$E$2)) -> 345 | G12: =IF(ISNUMBER(F12),F12*H12,0) -> 0 | H12: 0
A13: Company formation | B13: LLP | C13: 213 | D13: inc VAT | E13: =IF(ISNUMBER(C13),IF(D13="inc VAT",C13/1.2,C13),0) -> 177.5 | F13: =IF(E13=0,"POA",CEILING(E13*(1+$B$2),$E$2)) -> 270 | G13: =IF(ISNUMBER(F13),F13*H13,0) -> 0 | H13: 0
A14: Company formation | B14: Right to Manage | C14: 223 | D14: inc VAT | E14: =IF(ISNUMBER(C14),IF(D14="inc VAT",C14/1.2,C14),0) -> 185.83333 | F14: =IF(E14=0,"POA",CEILING(E14*(1+$B$2),$E$2)) -> 280 | G14: =IF(ISNUMBER(F14),F14*H14,0) -> 0 | H14: 0
A15: Company formation | B15: CIO | C15: 458 | D15: inc VAT | E15: =IF(ISNUMBER(C15),IF(D15="inc VAT",C15/1.2,C15),0) -> 381.66667 | F15: =IF(E15=0,"POA",CEILING(E15*(1+$B$2),$E$2)) -> 575 | G15: =IF(ISNUMBER(F15),F15*H15,0) -> 0 | H15: 0
A16: Company formation | B16: Unlimited | C16: 358 | D16: inc VAT | E16: =IF(ISNUMBER(C16),IF(D16="inc VAT",C16/1.2,C16),0) -> 298.33333 | F16: =IF(E16=0,"POA",CEILING(E16*(1+$B$2),$E$2)) -> 450 | G16: =IF(ISNUMBER(F16),F16*H16,0) -> 0 | H16: 0
A17: Company formation | B17: LP | C17: 178 | D17: inc VAT | E17: =IF(ISNUMBER(C17),IF(D17="inc VAT",C17/1.2,C17),0) -> 148.33333 | F17: =IF(E17=0,"POA",CEILING(E17*(1+$B$2),$E$2)) -> 225 | G17: =IF(ISNUMBER(F17),F17*H17,0) -> 0 | H17: 0
A18: Company formation | B18: B-Corp | C18: 183 | D18: inc VAT | E18: =IF(ISNUMBER(C18),IF(D18="inc VAT",C18/1.2,C18),0) -> 152.5 | F18: =IF(E18=0,"POA",CEILING(E18*(1+$B$2),$E$2)) -> 230 | G18: =IF(ISNUMBER(F18),F18*H18,0) -> 0 | H18: 0
A19: Company formation | B19: Ready Made company | C19: 203 | D19: inc VAT | E19: =IF(ISNUMBER(C19),IF(D19="inc VAT",C19/1.2,C19),0) -> 169.16667 | F19: =IF(E19=0,"POA",CEILING(E19*(1+$B$2),$E$2)) -> 255 | G19: =IF(ISNUMBER(F19),F19*H19,0) -> 0 | H19: 0
... A25: Company formation | B25: Add-on: register for unlimited | C25: 75 | D25: inc VAT | E25: =IF(ISNUMBER(C25),IF(D25="inc VAT",C25/1.2,C25),0) -> 62.5 | F25: =IF(E25=0,"POA",CEILING(E25*(1+$B$2),$E$2)) -> 95 | G25: =IF(ISNUMBER(F25),F25*H25,0) -> 0 | H25: 0
A26: Share & capital work
A27: Share & capital work | B27: Share restructure – standard class shares (e.g. alphabet shares) | C27: 200 | D27: ex VAT | E27: =IF(ISNUMBER(C27),IF(D27="inc VAT",C27/1.2,C27),0) -> 200 | F27: =IF(E27=0,"POA",CEILING(E27*(1+$B$2),$E$2)) -> 300 | G27: =IF(ISNUMBER(F27),F27*H27,0) -> 0 | H27: 0 | I27: ='Rate Card'!$B$41 -> 450 | J27: FCLS does the legal paperwork only – your £450 also covers the tax note
A28: Share & capital work | B28: Share restructure with allotments and/or transfers | C28: 220 | D28: ex VAT | E28: =IF(ISNUMBER(C28),IF(D28="inc VAT",C28/1.2,C28),0) -> 220 | F28: =IF(E28=0,"POA",CEILING(E28*(1+$B$2),$E$2)) -> 330 | G28: =IF(ISNUMBER(F28),F28*H28,0) -> 0 | H28: 0
A29: Share & capital work | B29: Share restructure incl. bonus issue or sub-division | C29: 250 | D29: ex VAT | E29: =IF(ISNUMBER(C29),IF(D29="inc VAT",C29/1.2,C29),0) -> 250 | F29: =IF(E29=0,"POA",CEILING(E29*(1+$B$2),$E$2)) -> 375 | G29: =IF(ISNUMBER(F29),F29*H29,0) -> 0 | H29: 0
A30: Share & capital work | B30: Share restructure incl. redeemable preference shares | C30: 250 | D30: ex VAT | E30: =IF(ISNUMBER(C30),IF(D30="inc VAT",C30/1.2,C30),0) -> 250 | F30: =IF(E30=0,"POA",CEILING(E30*(1+$B$2),$E$2)) -> 375 | G30: =IF(ISNUMBER(F30),F30*H30,0) -> 0 | H30: 0
A31: Share & capital work | B31: Purchase of own shares | C31: 230 | D31: ex VAT | E31: =IF(ISNUMBER(C31),IF(D31="inc VAT",C31/1.2,C31),0) -> 230 | F31: =IF(E31=0,"POA",CEILING(E31*(1+$B$2),$E$2)) -> 345 | G31: =IF(ISNUMBER(F31),F31*H31,0) -> 0 | H31: 0
A32: Share & capital work | B32: Purchase of own shares – out of cash with articles | C32: 400 | D32: ex VAT | E32: =IF(ISNUMBER(C32),IF(D32="inc VAT",C32/1.2,C32),0) -> 400 | F32: =IF(E32=0,"POA",CEILING(E32*(1+$B$2),$E$2)) -> 600 | G32: =IF(ISNUMBER(F32),F32*H32,0) -> 0 | H32: 0
A33: Share & capital work | B33: Purchase of own shares – out of capital | C33: 500 | D33: ex VAT | E33: =IF(ISNUMBER(C33),IF(D33="inc VAT",C33/1.2,C33),0) -> 500 | F33: =IF(E33=0,"POA",CEILING(E33*(1+$B$2),$E$2)) -> 750 | G33: =IF(ISNUMBER(F33),F33*H33,0) -> 0 | H33: 0
A34: Share & capital work | B34: Reduction of capital | C34: 230 | D34: ex VAT | E34: =IF(ISNUMBER(C34),IF(D34="inc VAT",C34/1.2,C34),0) -> 230 | F34: =IF(E34=0,"POA",CEILING(E34*(1+$B$2),$E$2)) -> 345 | G34: =IF(ISNUMBER(F34),F34*H34,0) -> 0 | H34: 0
A35: Share & capital work | B35: Share for share exchange | C35: 220 | D35: ex VAT | E35: =IF(ISNUMBER(C35),IF(D35="inc VAT",C35/1.2,C35),0) -> 220 | F35: =IF(E35=0,"POA",CEILING(E35*(1+$B$2),$E$2)) -> 330 | G35: =IF(ISNUMBER(F35),F35*H35,0) -> 0 | H35: 0
A36: Share & capital work | B36: Sub-division or consolidation | C36: 200 | D36: ex VAT | E36: =IF(ISNUMBER(C36),IF(D36="inc VAT",C36/1.2,C36),0) -> 200 | F36: =IF(E36=0,"POA",CEILING(E36*(1+$B$2),$E$2)) -> 300 | G36: =IF(ISNUMBER(F36),F36*H36,0) -> 0 | H36: 0
A37: Share & capital work | B37: Redemption | C37: 130 | D37: ex VAT | E37: =IF(ISNUMBER(C37),IF(D37="inc VAT",C37/1.2,C37),0) -> 130 | F37: =IF(E37=0,"POA",CEILING(E37*(1+$B$2),$E$2)) -> 195 | G37: =IF(ISNUMBER(F37),F37*H37,0) -> 0 | H37: 0
A38: Share & capital work | B38: Bonus or rights issue | C38: 160 | D38: ex VAT | E38: =IF(ISNUMBER(C38),IF(D38="inc VAT",C38/1.2,C38),0) -> 160 | F38: =IF(E38=0,"POA",CEILING(E38*(1+$B$2),$E$2)) -> 240 | G38: =IF(ISNUMBER(F38),F38*H38,0) -> 0 | H38: 0
A39: Share & capital work | B39: Allotment | C39: 120 | D39: ex VAT | E39: =IF(ISNUMBER(C39),IF(D39="inc VAT",C39/1.2,C39),0) -> 120 | F39: =IF(E39=0,"POA",CEILING(E39*(1+$B$2),$E$2)) -> 180 | G39: =IF(ISNUMBER(F39),F39*H39,0) -> 0 | H39: 0 | I39: ='Rate Card'!$B$42 -> 150
A40: Share & capital work | B40: Transfer | C40: 70 | D40: ex VAT | E40: =IF(ISNUMBER(C40),IF(D40="inc VAT",C40/1.2,C40),0) -> 70 | F40: =IF(E40=0,"POA",CEILING(E40*(1+$B$2),$E$2)) -> 105 | G40: =IF(ISNUMBER(F40),F40*H40,0) -> 0 | H40: 0 | I40: ='Rate Card'!$B$42 -> 150
A41: Other company services
A42: Other company services | B42: Update of articles | C42: 200 | D42: ex VAT | E42: =IF(ISNUMBER(C42),IF(D42="inc VAT",C42/1.2,C42),0) -> 200 | F42: =IF(E42=0,"POA",CEILING(E42*(1+$B$2),$E$2)) -> 300 | G42: =IF(ISNUMBER(F42),F42*H42,0) -> 0 | H42: 0
A43: Other company services | B43: Electronic change of name | C43: 62 | D43: ex VAT | E43: =IF(ISNUMBER(C43),IF(D43="inc VAT",C43/1.2,C43),0) -> 62 | F43: =IF(E43=0,"POA",CEILING(E43*(1+$B$2),$E$2)) -> 95 | G43: =IF(ISNUMBER(F43),F43*H43,0) -> 0 | H43: 0
A44: Other company services | B44: Simultaneous change of name | C44: 220 | D44: ex VAT | E44: =IF(ISNUMBER(C44),IF(D44="inc VAT",C44/1.2,C44),0) -> 220 | F44: =IF(E44=0,"POA",CEILING(E44*(1+$B$2),$E$2)) -> 330 | G44: =IF(ISNUMBER(F44),F44*H44,0) -> 0 | H44: 0
A45: Other company services | B45: Re-registration / conversion | C45: 400 | D45: ex VAT | E45: =IF(ISNUMBER(C45),IF(D45="inc VAT",C45/1.2,C45),0) -> 400 | F45: =IF(E45=0,"POA",CEILING(E45*(1+$B$2),$E$2)) -> 600 | G45: =IF(ISNUMBER(F45),F45*H45,0) -> 0 | H45: 0
A46: Other company services | B46: Reconstruction of statutory registers | C46: POA | D46: ex VAT | E46: =IF(ISNUMBER(C46),IF(D46="inc VAT",C46/1.2,C46),0) -> 0 | F46: =IF(E46=0,"POA",CEILING(E46*(1+$B$2),$E$2)) -> POA | G46: =IF(ISNUMBER(F46),F46*H46,0) -> 0 | H46: 0
A47: Other company services | B47: Typesetting of articles | C47: POA | D47: ex VAT | E47: =IF(ISNUMBER(C47),IF(D47="inc VAT",C47/1.2,C47),0) -> 0 | F47: =IF(E47=0,"POA",CEILING(E47*(1+$B$2),$E$2)) -> POA | G47: =IF(ISNUMBER(F47),F47*H47,0) -> 0 | H47: 0
A48: Other company services | B48: Company health check | C48: 40 | D48: ex VAT | E48: =IF(ISNUMBER(C48),IF(D48="inc VAT",C48/1.2,C48),0) -> 40 | F48: =IF(E48=0,"POA",CEILING(E48*(1+$B$2),$E$2)) -> 60 | G48: =IF(ISNUMBER(F48),F48*H48,0) -> 0 | H48: 0
A49: Other company services | B49: Certificate of good standing – apostille | C49: 235 | D49: ex VAT | E49: =IF(ISNUMBER(C49),IF(D49="inc VAT",C49/1.2,C49),0) -> 235 | F49: =IF(E49=0,"POA",CEILING(E49*(1+$B$2),$E$2)) -> 355 | G49: =IF(ISNUMBER(F49),F49*H49,0) -> 0 | H49: 0
A50: Other company services | B50: Administrative restoration (plus disbursements) | C50: 300 | D50: ex VAT | E50: =IF(ISNUMBER(C50),IF(D50="inc VAT",C50/1.2,C50),0) -> 300 | F50: =IF(E50=0,"POA",CEILING(E50*(1+$B$2),$E$2)) -> 450 | G50: =IF(ISNUMBER(F50),F50*H50,0) -> 0 | H50: 0
A51: Other company services | B51: Court restoration (plus disbursements) | C51: 1000 | D51: ex VAT | E51: =IF(ISNUMBER(C51),IF(D51="inc VAT",C51/1.2,C51),0) -> 1000 | F51: =IF(E51=0,"POA",CEILING(E51*(1+$B$2),$E$2)) -> 1500 | G51: =IF(ISNUMBER(F51),F51*H51,0) -> 0 | H51: 0
A52: Other company services | B52: Company ratification service | C52: 250 | D52: ex VAT | E52: =IF(ISNUMBER(C52),IF(D52="inc VAT",C52/1.2,C52),0) -> 250 | F52: =IF(E52=0,"POA",CEILING(E52*(1+$B$2),$E$2)) -> 375 | G52: =IF(ISNUMBER(F52),F52*H52,0) -> 0 | H52: 0
A53: Law stationery
A54: Law stationery | B54: Loose-leaf ring binder with slip cover | C54: 45 | D54: ex VAT | E54: =IF(ISNUMBER(C54),IF(D54="inc VAT",C54/1.2,C54),0) -> 45 | F54: =IF(E54=0,"POA",CEILING(E54*(1+$B$2),$E$2)) -> 70 | G54: =IF(ISNUMBER(F54),F54*H54,0) -> 0 | H54: 0
A55: Law stationery | B55: Hand plier seal | C55: 40 | D55: ex VAT | E55: =IF(ISNUMBER(C55),IF(D55="inc VAT",C55/1.2,C55),0) -> 40 | F55: =IF(E55=0,"POA",CEILING(E55*(1+$B$2),$E$2)) -> 60 | G55: =IF(ISNUMBER(F55),F55*H55,0) -> 0 | H55: 0
A56: Law stationery | B56: Loose-leaf ring binder | C56: 35 | D56: ex VAT | E56: =IF(ISNUMBER(C56),IF(D56="inc VAT",C56/1.2,C56),0) -> 35 | F56: =IF(E56=0,"POA",CEILING(E56*(1+$B$2),$E$2)) -> 55 | G56: =IF(ISNUMBER(F56),F56*H56,0) -> 0 | H56: 0
A57: Law stationery | B57: Bound copy of articles (per copy) | C57: 5 | D57: ex VAT | E57: =IF(ISNUMBER(C57),IF(D57="inc VAT",C57/1.2,C57),0) -> 5 | F57: =IF(E57=0,"POA",CEILING(E57*(1+$B$2),$E$2)) -> 10 | G57: =IF(ISNUMBER(F57),F57*H57,0) -> 0 | H57: 0
A58: Law stationery | B58: Soft bound register | C58: 30 | D58: ex VAT | E58: =IF(ISNUMBER(C58),IF(D58="inc VAT",C58/1.2,C58),0) -> 30 | F58: =IF(E58=0,"POA",CEILING(E58*(1+$B$2),$E$2)) -> 45 | G58: =IF(ISNUMBER(F58),F58*H58,0) -> 0 | H58: 0
A59: ECCTA identity verification
A60: ECCTA identity verification | B60: Verification & registration | C60: 35 | D60: ex VAT | E60: =IF(ISNUMBER(C60),IF(D60="inc VAT",C60/1.2,C60),0) -> 35 | F60: =IF(E60=0,"POA",CEILING(E60*(1+$B$2),$E$2)) -> 55 | G60: =IF(ISNUMBER(F60),F60*H60,0) -> 0 | H60: 0
A61: ECCTA identity verification | B61: Manual verification | C61: 50 | D61: ex VAT | E61: =IF(ISNUMBER(C61),IF(D61="inc VAT",C61/1.2,C61),0) -> 50 | F61: =IF(E61=0,"POA",CEILING(E61*(1+$B$2),$E$2)) -> 75 | G61: =IF(ISNUMBER(F61),F61*H61,0) -> 0 | H61: 0
A62: ECCTA identity verification | B62: PSCVS01 filing | C62: 45 | D62: ex VAT | E62: =IF(ISNUMBER(C62),IF(D62="inc VAT",C62/1.2,C62),0) -> 45 | F62: =IF(E62=0,"POA",CEILING(E62*(1+$B$2),$E$2)) -> 70 | G62: =IF(ISNUMBER(F62),F62*H62,0) -> 0 | H62: 0
A63: Secretarial software & outsourcing
A64: Secretarial software & outsourcing | B64: First Order secretarial software (from, per company) | C64: 5 | D64: ex VAT | E64: =IF(ISNUMBER(C64),IF(D64="inc VAT",C64/1.2,C64),0) -> 5 | F64: =IF(E64=0,"POA",CEILING(E64*(1+$B$2),$E$2)) -> 10 | G64: =IF(ISNUMBER(F64),F64*H64,0) -> 0 | H64: 0
A65: Secretarial software & outsourcing | B65: Secretarial outsourcing (from, per company) | C65: 35 | D65: ex VAT | E65: =IF(ISNUMBER(C65),IF(D65="inc VAT",C65/1.2,C65),0) -> 35 | F65: =IF(E65=0,"POA",CEILING(E65*(1+$B$2),$E$2)) -> 55 | G65: =IF(ISNUMBER(F65),F65*H65,0) -> 0 | H65: 0
A66: Nominee services
A67: Nominee services | B67: Registered office | C67: 100 | D67: ex VAT | E67: =IF(ISNUMBER(C67),IF(D67="inc VAT",C67/1.2,C67),0) -> 100 | F67: =IF(E67=0,"POA",CEILING(E67*(1+$B$2),$E$2)) -> 150 | G67: =IF(ISNUMBER(F67),F67*H67,0) -> 0 | H67: 0 | I67: ='Rate Card'!$B$34 -> 120
A68: Nominee services | B68: Nominee secretary | C68: 95 | D68: ex VAT | E68: =IF(ISNUMBER(C68),IF(D68="inc VAT",C68/1.2,C68),0) -> 95 | F68: =IF(E68=0,"POA",CEILING(E68*(1+$B$2),$E$2)) -> 145 | G68: =IF(ISNUMBER(F68),F68*H68,0) -> 0 | H68: 0
A69: Nominee services | B69: Nominee shareholder | C69: 150 | D69: ex VAT | E69: =IF(ISNUMBER(C69),IF(D69="inc VAT",C69/1.2,C69),0) -> 150 | F69: =IF(E69=0,"POA",CEILING(E69*(1+$B$2),$E$2)) -> 225 | G69: =IF(ISNUMBER(F69),F69*H69,0) -> 0 | H69: 0
A70: Nominee services | B70: Nominee director | C70: 2500 | D70: ex VAT | E70: =IF(ISNUMBER(C70),IF(D70="inc VAT",C70/1.2,C70),0) -> 2500 | F70: =IF(E70=0,"POA",CEILING(E70*(1+$B$2),$E$2)) -> 3750 | G70: =IF(ISNUMBER(F70),F70*H70,0) -> 0 | H70: 0
A71: Agreements
A72: Agreements | B72: Shareholder agreement | C72: 900 | D72: ex VAT | E72: =IF(ISNUMBER(C72),IF(D72="inc VAT",C72/1.2,C72),0) -> 900 | F72: =IF(E72=0,"POA",CEILING(E72*(1+$B$2),$E$2)) -> 1350 | G72: =IF(ISNUMBER(F72),F72*H72,0) -> 0 | H72: 0
A73: Agreements | B73: Loan agreement | C73: 600 | D73: ex VAT | E73: =IF(ISNUMBER(C73),IF(D73="inc VAT",C73/1.2,C73),0) -> 600 | F73: =IF(E73=0,"POA",CEILING(E73*(1+$B$2),$E$2)) -> 900 | G73: =IF(ISNUMBER(F73),F73*H73,0) -> 0 | H73: 0
A74: Agreements | B74: Partnership agreement | C74: 650 | D74: ex VAT | E74: =IF(ISNUMBER(C74),IF(D74="inc VAT",C74/1.2,C74),0) -> 650 | F74: =IF(E74=0,"POA",CEILING(E74*(1+$B$2),$E$2)) -> 975 | G74: =IF(ISNUMBER(F74),F74*H74,0) -> 0 | H74: 0
A75: Company searches
A76: Company searches | B76: Winding up search | C76: 30 | D76: inc VAT | E76: =IF(ISNUMBER(C76),IF(D76="inc VAT",C76/1.2,C76),0) -> 25 | F76: =IF(E76=0,"POA",CEILING(E76*(1+$B$2),$E$2)) -> 40 | G76: =IF(ISNUMBER(F76),F76*H76,0) -> 0 | H76: 0
A77: Company searches | B77: Full search and winding up search | C77: 38 | D77: inc VAT | E77: =IF(ISNUMBER(C77),IF(D77="inc VAT",C77/1.2,C77),0) -> 31.666667 | F77: =IF(E77=0,"POA",CEILING(E77*(1+$B$2),$E$2)) -> 50 | G77: =IF(ISNUMBER(F77),F77*H77,0) -> 0 | H77: 0
A78: Company searches | B78: Full search with accounts | C78: 32 | D78: inc VAT | E78: =IF(ISNUMBER(C78),IF(D78="inc VAT",C78/1.2,C78),0) -> 26.666667 | F78: =IF(E78=0,"POA",CEILING(E78*(1+$B$2),$E$2)) -> 40 | G78: =IF(ISNUMBER(F78),F78*H78,0) -> 0 | H78: 0
A79: Company searches | B79: Full search without accounts | C79: 27 | D79: inc VAT | E79: =IF(ISNUMBER(C79),IF(D79="inc VAT",C79/1.2,C79),0) -> 22.5 | F79: =IF(E79=0,"POA",CEILING(E79*(1+$B$2),$E$2)) -> 35 | G79: =IF(ISNUMBER(F79),F79*H79,0) -> 0 | H79: 0
A80: Company searches | B80: Latest accounts or annual return | C80: 21 | D80: inc VAT | E80: =IF(ISNUMBER(C80),IF(D80="inc VAT",C80/1.2,C80),0) -> 17.5 | F80: =IF(E80=0,"POA",CEILING(E80*(1+$B$2),$E$2)) -> 30 | G80: =IF(ISNUMBER(F80),F80*H80,0) -> 0 | H80: 0
A81: Company searches | B81: Latest accounts and annual return | C81: 24 | D81: inc VAT | E81: =IF(ISNUMBER(C81),IF(D81="inc VAT",C81/1.2,C81),0) -> 20 | F81: =IF(E81=0,"POA",CEILING(E81*(1+$B$2),$E$2)) -> 30 | G81: =IF(ISNUMBER(F81),F81*H81,0) -> 0 | H81: 0
A82: Company searches | B82: Copy of memorandum & articles | C82: 21 | D82: inc VAT | E82: =IF(ISNUMBER(C82),IF(D82="inc VAT",C82/1.2,C82),0) -> 17.5 | F82: =IF(E82=0,"POA",CEILING(E82*(1+$B$2),$E$2)) -> 30 | G82: =IF(ISNUMBER(F82),F82*H82,0) -> 0 | H82: 0
A83: Company searches | B83: Conveyancing search – under 50 charges | C83: 32 | D83: inc VAT | E83: =IF(ISNUMBER(C83),IF(D83="inc VAT",C83/1.2,C83),0) -> 26.666667 | F83: =IF(E83=0,"POA",CEILING(E83*(1+$B$2),$E$2)) -> 40 | G83: =IF(ISNUMBER(F83),F83*H83,0) -> 0 | H83: 0
A84: Company searches | B84: Conveyancing search – over 50 charges | C84: POA | D84: inc VAT | E84: =IF(ISNUMBER(C84),IF(D84="inc VAT",C84/1.2,C84),0) -> 0 | F84: =IF(E84=0,"POA",CEILING(E84*(1+$B$2),$E$2)) -> POA | G84: =IF(ISNUMBER(F84),F84*H84,0) -> 0 | H84: 0
A85: Company searches | B85: Directors search | C85: 18 | D85: inc VAT | E85: =IF(ISNUMBER(C85),IF(D85="inc VAT",C85/1.2,C85),0) -> 15 | F85: =IF(E85=0,"POA",CEILING(E85*(1+$B$2),$E$2)) -> 25 | G85: =IF(ISNUMBER(F85),F85*H85,0) -> 0 | H85: 0
A86: Company searches | B86: Registered office search | C86: 14 | D86: inc VAT | E86: =IF(ISNUMBER(C86),IF(D86="inc VAT",C86/1.2,C86),0) -> 11.666667 | F86: =IF(E86=0,"POA",CEILING(E86*(1+$B$2),$E$2)) -> 20 | G86: =IF(ISNUMBER(F86),F86*H86,0) -> 0 | H86: 0
A87: Company searches | B87: Credit report | C87: 48 | D87: inc VAT | E87: =IF(ISNUMBER(C87),IF(D87="inc VAT",C87/1.2,C87),0) -> 40 | F87: =IF(E87=0,"POA",CEILING(E87*(1+$B$2),$E$2)) -> 60 | G87: =IF(ISNUMBER(F87),F87*H87,0) -> 0 | H87: 0
A88: Company searches | B88: International searches and IP | C88: POA | D88: inc VAT | E88: =IF(ISNUMBER(C88),IF(D88="inc VAT",C88/1.2,C88),0) -> 0 | F88: =IF(E88=0,"POA",CEILING(E88*(1+$B$2),$E$2)) -> POA | G88: =IF(ISNUMBER(F88),F88*H88,0) -> 0 | H88: 0
A89: Additional filing services
A90: Additional filing services | B90: Filing of confirmation statement | C90: 80 | D90: ex VAT | E90: =IF(ISNUMBER(C90),IF(D90="inc VAT",C90/1.2,C90),0) -> 80 | F90: =IF(E90=0,"POA",CEILING(E90*(1+$B$2),$E$2)) -> 120 | G90: =IF(ISNUMBER(F90),F90*H90,0) -> 0 | H90: 0 | I90: ='Rate Card'!$B$32 -> 60 | J90: Your fee shown excludes the Companies House fee
A91: Additional filing services | B91: Filing of DS01 to dissolve company | C91: 60 | D91: ex VAT | E91: =IF(ISNUMBER(C91),IF(D91="inc VAT",C91/1.2,C91),0) -> 60 | F91: =IF(E91=0,"POA",CEILING(E91*(1+$B$2),$E$2)) -> 90 | G91: =IF(ISNUMBER(F91),F91*H91,0) -> 0 | H91: 0
A92: Additional filing services | B92: Appointment of director/secretary | C92: 50 | D92: ex VAT | E92: =IF(ISNUMBER(C92),IF(D92="inc VAT",C92/1.2,C92),0) -> 50 | F92: =IF(E92=0,"POA",CEILING(E92*(1+$B$2),$E$2)) -> 75 | G92: =IF(ISNUMBER(F92),F92*H92,0) -> 0 | H92: 0
A93: Additional filing services | B93: Resignation of director/secretary | C93: 30 | D93: ex VAT | E93: =IF(ISNUMBER(C93),IF(D93="inc VAT",C93/1.2,C93),0) -> 30 | F93: =IF(E93=0,"POA",CEILING(E93*(1+$B$2),$E$2)) -> 45 | G93: =IF(ISNUMBER(F93),F93*H93,0) -> 0 | H93: 0
A94: Additional filing services | B94: Change of address (company or person) | C94: 25 | D94: ex VAT | E94: =IF(ISNUMBER(C94),IF(D94="inc VAT",C94/1.2,C94),0) -> 25 | F94: =IF(E94=0,"POA",CEILING(E94*(1+$B$2),$E$2)) -> 40 | G94: =IF(ISNUMBER(F94),F94*H94,0) -> 0 | H94: 0
A95: Additional filing services | B95: Second filing of an incorrect document | C95: 50 | D95: ex VAT | E95: =IF(ISNUMBER(C95),IF(D95="inc VAT",C95/1.2,C95),0) -> 50 | F95: =IF(E95=0,"POA",CEILING(E95*(1+$B$2),$E$2)) -> 75 | G95: =IF(ISNUMBER(F95),F95*H95,0) -> 0 | H95: 0
A96: Additional filing services | B96: Share certificate (PDF, each) | C96: 15 | D96: ex VAT | E96: =IF(ISNUMBER(C96),IF(D96="inc VAT",C96/1.2,C96),0) -> 15 | F96: =IF(E96=0,"POA",CEILING(E96*(1+$B$2),$E$2)) -> 25 | G96: =IF(ISNUMBER(F96),F96*H96,0) -> 0 | H96: 0
A97: Additional filing services | B97: Correspondence address at Companies House (per person) | C97: 40 | D97: ex VAT | E97: =IF(ISNUMBER(C97),IF(D97="inc VAT",C97/1.2,C97),0) -> 40 | F97: =IF(E97=0,"POA",CEILING(E97*(1+$B$2),$E$2)) -> 60 | G97: =IF(ISNUMBER(F97),F97*H97,0) -> 0 | H97: 0
A98: Additional filing services | B98: PSC change (single) | C98: 45 | D98: ex VAT | E98: =IF(ISNUMBER(C98),IF(D98="inc VAT",C98/1.2,C98),0) -> 45 | F98: =IF(E98=0,"POA",CEILING(E98*(1+$B$2),$E$2)) -> 70 | G98: =IF(ISNUMBER(F98),F98*H98,0) -> 0 | H98: 0
A99: Additional filing services | B99: Each additional PSC change | C99: 30 | D99: ex VAT | E99: =IF(ISNUMBER(C99),IF(D99="inc VAT",C99/1.2,C99),0) -> 30 | F99: =IF(E99=0,"POA",CEILING(E99*(1+$B$2),$E$2)) -> 45 | G99: =IF(ISNUMBER(F99),F99*H99,0) -> 0 | H99: 0
A100: Additional filing services | B100: Correction of date of birth (each) | C100: 75 | D100: ex VAT | E100: =IF(ISNUMBER(C100),IF(D100="inc VAT",C100/1.2,C100),0) -> 75 | F100: =IF(E100=0,"POA",CEILING(E100*(1+$B$2),$E$2)) -> 115 | G100: =IF(ISNUMBER(F100),F100*H100,0) -> 0 | H100: 0
A101: Additional filing services | B101: Correction of date of birth (both PSC & director) | C101: 100 | D101: ex VAT | E101: =IF(ISNUMBER(C101),IF(D101="inc VAT",C101/1.2,C101),0) -> 100 | F101: =IF(E101=0,"POA",CEILING(E101*(1+$B$2),$E$2)) -> 150 | G101: =IF(ISNUMBER(F101),F101*H101,0) -> 0 | H101: 0
A102: Additional filing services | B102: PSC & director appointment | C102: 75 | D102: ex VAT | E102: =IF(ISNUMBER(C102),IF(D102="inc VAT",C102/1.2,C102),0) -> 75 | F102: =IF(E102=0,"POA",CEILING(E102*(1+$B$2),$E$2)) -> 115 | G102: =IF(ISNUMBER(F102),F102*H102,0) -> 0 | H102: 0
... A104: Additional filing services | B104: Director OR PSC verification, registration & appointment | C104: 75 | D104: ex VAT | E104: =IF(ISNUMBER(C104),IF(D104="inc VAT",C104/1.2,C104),0) -> 75 | F104: =IF(E104=0,"POA",CEILING(E104*(1+$B$2),$E$2)) -> 115 | G104: =IF(ISNUMBER(F104),F104*H104,0) -> 0 | H104: 0
A105: Additional filing services | B105: Dormant accounts filing | C105: 35 | D105: ex VAT | E105: =IF(ISNUMBER(C105),IF(D105="inc VAT",C105/1.2,C105),0) -> 35 | F105: =IF(E105=0,"POA",CEILING(E105*(1+$B$2),$E$2)) -> 55 | G105: =IF(ISNUMBER(F105),F105*H105,0) -> 0 | H105: 0 | I105: ='Rate Card'!$B$43 -> 150 | J105: Your £150 includes preparing the accounts
A106: Additional filing services | B106: Registered office and confirmation statement filing | C106: 160 | D106: ex VAT | E106: =IF(ISNUMBER(C106),IF(D106="inc VAT",C106/1.2,C106),0) -> 160 | F106: =IF(E106=0,"POA",CEILING(E106*(1+$B$2),$E$2)) -> 240 | G106: =IF(ISNUMBER(F106),F106*H106,0) -> 0 | H106: 0
A108: Source: FCLS Price List 2026 (Feb 26), supplied by George. FCLS prices marked 'inc VAT' are converted at 20%; formations also include the Companies House fee, so their ex-VAT cost is approximate. POA = price on application.

Sheet Competitor Research
A1: Hertfordshire competitor pricing research (gathered 23–24 Oct 2026 from public web pages)
A2: Figures are advertised 'from' prices or published ranges, ex VAT unless stated. Not verified with the firms – treat as indicative and re-check before relying on them.
A4: Firm / source | B4: Area | C4: Type | D4: Pricing model | E4: Sole trader | F4: Limited company | G4: Self assessment | H4: Bookkeeping | I4: VAT | J4: Payroll | K4: Other | L4: What to learn | M4: Source
A5: A-Wise Accountants | B5: Hertford, Hatfield, Hemel, Watford, WGC, Hitchin | C5: Online/low-cost chain (town landing pages) | D5: Headline monthly package with 'was/now' discount | E5: From £10/m (shown discounted to £5) | F5: From £40/m (shown discounted to £20) | G5: Not published | H5: Not published | I5: Not published | J5: Not published | K5: Same page cloned per town for local SEO | L5: Low anchor price wins clicks; the real fee comes from add-ons. Expect clients to quote '£20 a month' at you – show what's excluded. | M5: https://a-wise.co.uk/accountants-in-hertford/
A6: RSBC | B6: St Albans, Hitchin, WGC | C6: Online/low-cost chain | D6: Tiered monthly packages | E6: £35/m + VAT | F6: £40/m + VAT | G6: Included in packages (scope unclear) | H6: Package from £35/m | I6: Not published | J6: Not published | K6: 'From £10 pm' headline | L6: Two simple price points by entity type – easy for a client to understand and buy online. | M6: https://www.rsbc.uk/accountants-in-st-albans
A7: Mazuma (via St Albans page) | B7: St Albans | C7: National online bookkeeping | D7: Fixed monthly bookkeeping | E7: — | F7: — | G7: — | H7: From £38/m + VAT | I7: — | J7: — | K7: Page ~2 years old | L7: Bookkeeping as a standalone subscription, not bundled. | M7: https://www.yourstalbansaccountants.co.uk/bookkeeping
A8: St Albans fixed-fee SA provider | B8: St Albans | C8: Specialist / directory | D8: Fixed fee per return, tiered by client type | E8: — | F8: — | G8: £199 simple; £249 landlord; £299 company director (+VAT) | H8: — | I8: — | J8: — | K8: Another St Albans firm: £136 all-in | L8: Tiering SA by client type (simple / landlord / director) is a clean model – UFS uses add-ons instead. | M8: https://selfassessmenttaxreturn.accountants/self-assessment-tax-return-in-st-albans/
A9: DiGiFiLiNG | B9: St Albans | C9: Online | D9: Fixed fee | E9: — | F9: — | G9: From £199 | H9: — | I9: — | J9: — | L9: Confirms ~£199 as the local anchor for a simple return. | M9: https://digifiling.co.uk/areas-we-serve/small-business-tax-accountant-in-st-albans-uk/
A10: Stevenage SA specialist | B10: Stevenage | C10: Specialist | D10: Fixed fee, filed before 31 Jan | E10: — | F10: — | G10: From £199 + VAT | H10: — | I10: — | J10: — | L10: Same £199 anchor. | M10: https://selfassessmenttaxreturn.accountants/self-assessment-tax-return-in-stevenage/
A11: WGC bookkeeping firm | B11: Welwyn Garden City | C11: Local bookkeeper | D11: Hours-capped monthly package | E11: — | F11: — | G11: — | H11: £79/m + VAT for up to 4 hrs (software extra) | I11: — | J11: — | L11: Capping by hours protects margin on messy clients – an alternative to UFS's per-transaction model. | M11: https://bookkeepingservices.accountants/small-businesses/welwyn-garden-city/
A12: WGC/St Albans hourly bookkeeper | B12: WGC / St Albans | C12: Local bookkeeper | D12: Hourly then move to fixed | E12: — | F12: Fixed Ltd package from £149/m | G12: — | H12: £15/hr + VAT | I12: — | J12: — | L12: Start hourly to learn the client's volume, then fix the fee – good for onboarding unknown clients. | M12: https://bookkeepingservices.accountants/bookkeeping-services/st-albans/
A13: Hertfordshire listing/directory | B13: Hertfordshire | C13: Directory price list | D13: Itemised menu | E13: — | F13: — | G13: — | H13: — | I13: £89/qtr + VAT | J13: £29/m + VAT up to 3 staff; +£10/m each extra | K13: Confirmation statement £92 + VAT | L13: An itemised menu makes add-ons visible and easy to upsell. | M13: https://www.accountingfirms.co.uk/app/services/payroll-services-in-hertfordshire
A14: Herts Accountants (blog) | B14: Hertfordshire | C14: Chartered firm | D14: Fixed annual fee bundle | E14: SA £150–£500/yr | F14: Accounts £500–£1,500/yr | G14: £150–£500 | H14: — | I14: £75–£200/qtr | J14: £5–£15 per employee/m | K14: No public monthly price – quote only | L14: Traditional firms hide price and sell on one agreed fixed fee covering everything. | M14: https://hertsaccountants.co.uk/blog/how-much-should-you-pay-accountant
A15: Blossom Accountants | B15: Hertfordshire | C15: Online | D15: Estimate ranges | E15: ~£30/m | F15: Up to £150+/m | G15: — | H15: — | I15: — | J15: — | K15: Says Herts sits mid-market | M15: https://blossomaccountants.co.uk/hertfordshire/
A16: VerifiedAccountants guide | B16: Hertfordshire / Hemel / WGC | C16: Fee guide | D16: Market ranges | E16: — | F16: Accounts + CT £750–£2,000/yr | G16: £150–£400 (most £200–£350) | H16: £100–£500/m | I16: £100–£300/qtr | J16: £50–£100/m minimum + £5–£15 per employee | K16: Monthly packages £100–£300; £300–£600 with bookkeeping, VAT, payroll | L16: Most useful benchmark for full-service fees. | M16: https://verifiedaccountants.co.uk/guides/accountant-cost/hertfordshire
A17: Bizhub365 guide | B17: Watford | C17: Fee guide | D17: Market ranges | E17: — | F17: £1,500–£3,500/yr | G17: £150–£300 | H17: — | I17: — | J17: — | K17: Hourly £50–£200 (Watford firm) | L17: Watford, nearer London, prices higher. | M17: https://www.bizhub365.com/find/accountant/watford/cost/
A18: KE Accounting Solutions | B18: Stevenage / Hertfordshire | C18: Local bookkeeping & accounts firm | D18: Tiered monthly packages by business size | E18: — | F18: £400/m basic Ltd (no staff); £750/m multi-staff payroll; £1,500/m full AP/AR & credit control | G18: — | H18: Hourly from £35/hr; entry packages from £150/m | I18: Included in tiers | J18: Included in tiers | K18: Xero/QuickBooks setup | L18: Premium positioning – sells outsourced finance function, not compliance. Shows the ceiling of the local market. | M18: https://keaccountingsolutions.co.uk/hertfordshire
A19: QK Accounts | B19: Beds / Herts / Bucks | C19: Online/regional | D19: Bronze/Silver/Gold bundles | E19: — | F19: Bronze £75/m (accounts, VAT, payroll up to 5); Silver £140/m; Gold £250/m | G19: — | H19: Standalone from £25/m | I19: Standalone £150/qtr | J19: Up to 5 staff in Bronze | K19: Free QuickBooks licence; Silver/Gold add monthly management meeting | L19: Good-better-best tiers with a 'meeting' upsell. Bundling VAT+payroll makes standalone VAT (£150) look expensive. | M19: https://www.qkaccounts.com/
A20: Connected Accounting (Bark) | B20: Hertfordshire | C20: Online, Xero partner | D20: Two flat packages | E20: £49/m + VAT (also landlords) | F20: £99/m + VAT | G20: Included | H20: Not stated | I20: Not stated | J20: Not stated | L20: Simple two-price model, landlords priced same as sole traders. | M20: https://www.bark.com/en/gb/bookkeeping-services/hertfordshire/
A21: Hertford hourly bookkeeper | B21: Hertford | C21: Local bookkeeper | D21: Hourly, no contract | E21: — | F21: — | G21: — | H21: £15/hr + VAT (Xero/QB/Sage) | I21: — | J21: — | K21: No monthly contract | L21: Low hourly rate – sets client expectation for basic data entry. | M21: https://bookkeepingservices.accountants/bookkeeping-services/hertford/
A22: Bishop's Stortford directory | B22: Bishop's Stortford | C22: Directory average | D22: Entry monthly price | E22: From £60/m + VAT | F22: From £95/m + VAT | G22: £150–£400/yr | H22: — | I22: — | J22: — | K22: Basic Ltd accounts £700–£1,200/yr | L22: East Herts entry prices sit above the online chains. | M22: https://businessfinancing.co.uk/accounting/bishops-stortford-accountants/
A23: Landlord specialist | B23: Bishop's Stortford | C23: Niche specialist | D23: Monthly retainer | E23: Landlords £100–£300/m | F23: — | G23: Included | H23: — | I23: — | J23: — | L23: Niche specialists charge well above general firms – landlord niche worth considering. | M23: https://accountants-for-landlords.co.uk/near-me/hertfordshire-bishops-stortford/
A24: Mazuma | B24: National online | C24: Online | D24: Monthly plans by turnover | E24: — | F24: £98–£140/m + VAT (~£1,176/yr+) | G24: — | H24: Included | I24: — | J24: — | L24: National online benchmark for a full Ltd package. | M24: https://taxroot.co.uk/blog/best-online-accountant-uk-2026
A25: Crunch | B25: National online | C25: Online | D25: Monthly subscription + one-off SA | E25: From £27/m + VAT | F25: Not stated in source | G25: £200 + VAT (rises near Jan deadline) | H25: Software-led | I25: — | J25: — | K25: Deadline surge pricing | L25: Charging more for late SA work rewards early clients and covers January overtime. | M25: https://taxroot.co.uk/blog/best-online-accountant-uk-2026
A26: Aardvark Accounting | B26: National online | C26: Online | D26: Monthly package | E26: — | F26: £89/m + VAT | G26: — | H26: — | I26: — | J26: — | M26: https://taxroot.co.uk/blog/best-online-accountant-uk-2026
A27: TaxRoot | B27: National online | C27: Online | D27: Annual compliance-only | E27: — | F27: From £389/yr (accounts, CT, CT600) | G27: — | H27: — | I27: — | J27: — | L27: Compliance-only pricing – the absolute floor for Ltd year-end. | M27: https://taxroot.co.uk/blog/best-online-accountant-uk-2026
A28: Price Bailey | B28: Bishop's Stortford | C28: Large regional chartered firm | D28: Bespoke quote | E28: — | F28: Not published | G28: — | H28: — | I28: — | J28: — | L28: Large firms don't publish prices – they compete on expertise and advisory. | M28: https://www.pricebailey.co.uk/locations/bishops-stortford/

Sheet Market Comparison
A1: UFS prices vs Hertfordshire market (ex VAT)
A2: Blue = market figures from Competitor Research tab. Green = live link to your Rate Card, so this updates when you change your prices.
A4: Service | B4: Unit | C4: Market low | D4: Market typical | E4: Market high | F4: UFS price | G4: Position | H4: UFS vs typical | I4: Evidence
A5: Self assessment – simple | B5: per return | C5: 136 | D5: 199 | E5: 350 | F5: ='Rate Card'!$B$25 -> 200 | G5: =IF(F5<C5,"Below market",IF(F5>E5,"Above market",IF(F5<D5,"Low end of range","High end of range"))) -> High end of range | H5: =IF(D5=0,0,F5/D5-1) -> 0.0050251256 | I5: £136 all-in / £199 x3 local firms / guide £150–£400
A6: Self assessment – landlord (1 property) | B6: per return | C6: 200 | D6: 249 | E6: 400 | F6: ='Rate Card'!$B$25+'Rate Card'!$B$26 -> 275 | G6: =IF(F6<C6,"Below market",IF(F6>E6,"Above market",IF(F6<D6,"Low end of range","High end of range"))) -> High end of range | H6: =IF(D6=0,0,F6/D6-1) -> 0.10441767 | I6: £249 St Albans; guide range
A7: Ltd accounts + CT600 (turnover £90k–£250k) | B7: per year | C7: 750 | D7: 1100 | E7: 2000 | F7: ='Rate Card'!$C$60+'Rate Card'!$B$24 -> 1100 | G7: =IF(F7<C7,"Below market",IF(F7>E7,"Above market",IF(F7<D7,"Low end of range","High end of range"))) -> High end of range | H7: =IF(D7=0,0,F7/D7-1) -> 0 | I7: Herts/Hemel guide £750–£2,000; Herts Accountants £500–£1,500 accounts only
A8: Ltd accounts + CT600 (under £90k) | B8: per year | C8: 500 | D8: 850 | E8: 1500 | F8: ='Rate Card'!$B$60+'Rate Card'!$B$24 -> 900 | G8: =IF(F8<C8,"Below market",IF(F8>E8,"Above market",IF(F8<D8,"Low end of range","High end of range"))) -> High end of range | H8: =IF(D8=0,0,F8/D8-1) -> 0.058823529 | I8: Herts Accountants accounts £500+; guide £750+
A9: VAT return | B9: per quarter | C9: 75 | D9: 100 | E9: 300 | F9: ='Rate Card'!$B$12 -> 75 | G9: =IF(F9<C9,"Below market",IF(F9>E9,"Above market",IF(F9<D9,"Low end of range","High end of range"))) -> Low end of range | H9: =IF(D9=0,0,F9/D9-1) -> -0.25 | I9: £75–£200 Herts Accountants; £89 listing; guide £100–£300
A10: Payroll – per employee | B10: per employee/month | C10: 5 | D10: 10 | E10: 15 | F10: ='Rate Card'!$B$17 -> 5 | G10: =IF(F10<C10,"Below market",IF(F10>E10,"Above market",IF(F10<D10,"Low end of range","High end of range"))) -> Low end of range | H10: =IF(D10=0,0,F10/D10-1) -> -0.5 | I10: £5–£15 guide and Herts Accountants; £10 extra staff on listing
A11: Payroll – minimum monthly | B11: per month | C11: 29 | D11: 50 | E11: 100 | F11: ='Rate Card'!$B$18 -> 20 | G11: =IF(F11<C11,"Below market",IF(F11>E11,"Above market",IF(F11<D11,"Low end of range","High end of range"))) -> Below market | H11: =IF(D11=0,0,F11/D11-1) -> -0.6 | I11: £29 listing (up to 3 staff); guide £50–£100 minimum
A12: Confirmation statement (your fee) | B12: per year | C12: 50 | D12: 60 | E12: 92 | F12: ='Rate Card'!$B$32 -> 60 | G12: =IF(F12<C12,"Below market",IF(F12>E12,"Above market",IF(F12<D12,"Low end of range","High end of range"))) -> High end of range | H12: =IF(D12=0,0,F12/D12-1) -> 0 | I12: £50 + filing fee; £92 listing
A13: Bookkeeping – entry level | B13: per month | C13: 35 | D13: 79 | E13: 149 | F13: ='Rate Card'!$B$5 -> 60 | G13: =IF(F13<C13,"Below market",IF(F13>E13,"Above market",IF(F13<D13,"Low end of range","High end of range"))) -> Low end of range | H13: =IF(D13=0,0,F13/D13-1) -> -0.24050633 | I13: £35 RSBC; £38 Mazuma; £79 (4 hrs) WGC; £149 Ltd fixed
A14: Bookkeeping – fuller service | B14: per month | C14: 100 | D14: 250 | E14: 500 | F14: ='Rate Card'!$B$5+70*'Rate Card'!$B$7 -> 116 | G14: =IF(F14<C14,"Below market",IF(F14>E14,"Above market",IF(F14<D14,"Low end of range","High end of range"))) -> Low end of range | H14: =IF(D14=0,0,F14/D14-1) -> -0.536 | I14: Guide £100–£500/m. UFS figure = base + 120 tx/month
A15: Ad hoc / advisory | B15: per hour | C15: 50 | D15: 100 | E15: 200 | F15: ='Rate Card'!$B$45 -> 90 | G15: =IF(F15<C15,"Below market",IF(F15>E15,"Above market",IF(F15<D15,"Low end of range","High end of range"))) -> Low end of range | H15: =IF(D15=0,0,F15/D15-1) -> -0.1 | I15: Watford £50–£200/hr
A16: Alphabet share restructure | B16: one-off | C16: 350 | D16: 450 | E16: 630 | F16: ='Rate Card'!$B$41 -> 450 | G16: =IF(F16<C16,"Below market",IF(F16>E16,"Above market",IF(F16<D16,"Low end of range","High end of range"))) -> High end of range | H16: =IF(D16=0,0,F16/D16-1) -> 0 | I16: Facebook group: £350–£450 accountants; £630 solicitor

Sheet Same Client Test
A1: Same client, priced under each competitor's model
A2: Client: Ltd company, £90k–£250k turnover, VAT registered, 3 staff on monthly payroll, 2 director SA returns, 120 transactions/month. Where a firm doesn't publish a fee, the market typical from Market Comparison is used (marked 'assumed').
A4: Firm / model | B4: Monthly package | C4: Bookkeeping /yr | D4: VAT /yr | E4: Payroll /yr | F4: SA x2 /yr | G4: Annual total (ex VAT) | H4: Notes
A5: UFS (your Quote Calculator) | G5: ='Quote Calculator'!C52 -> 5313.3 | H5: Your full recurring quote for the example client
A6: RSBC-style low-cost package | B6: 480 | C6: ='Market Comparison'!D13*12 -> 948 | D6: =4*'Market Comparison'!D9 -> 400 | E6: ='Market Comparison'!D11*12 -> 600 | F6: =2*'Market Comparison'!D5 -> 398 | G6: =SUM(B6:F6) -> 2826 | H6: Package £40/m; add-ons assumed at market typical
A7: A-Wise headline (discounted) | B7: 240 | C7: ='Market Comparison'!D13*12 -> 948 | D7: =4*'Market Comparison'!D9 -> 400 | E7: ='Market Comparison'!D11*12 -> 600 | F7: =2*'Market Comparison'!D5 -> 398 | G7: =SUM(B7:F7) -> 2586 | H7: £20/m headline; add-ons assumed
A8: Itemised menu (Herts listing) | B8: 0 | C8: ='Market Comparison'!D13*12 -> 948 | D8: =4*89 -> 356 | E8: =12*29 -> 348 | F8: =2*'Market Comparison'!D5 -> 398 | G8: =SUM(B8:F8)+'Market Comparison'!D7 -> 3150 | H8: £89 VAT and £29 payroll from listing; bookkeeping, SA and accounts+CT (£1,100) at market typical
A9: Traditional Herts firm (guide typical) | B9: 0 | C9: ='Market Comparison'!D13*12 -> 948 | D9: =4*'Market Comparison'!D9 -> 400 | E9: =MAX('Market Comparison'!D11,3*'Market Comparison'!D10)*12 -> 600 | F9: =2*'Market Comparison'!D5 -> 398 | G9: =SUM(B9:F9)+'Market Comparison'!D7 -> 3446 | H9: All at guide typical, incl. accounts+CT £1,100
A11: UFS vs cheapest competitor model | G11: =G5-MIN(G6:G9) -> 2727.3
A12: Note: UFS total includes management accounts, dividend paperwork, registered office and the records multiplier, which the others exclude. Compare like for like by switching those off in the Quote Calculator.
